{
  "id": 944,
  "common_name": "Dutchman's pipe",
  "scientific_name": [
    "Aristolochia tomentosa"
  ],
  "other_name": [],
  "family": "Aristolochiaceae",
  "hybrid": null,
  "authority": null,
  "subspecies": null,
  "cultivar": null,
  "variety": null,
  "species_epithet": "tomentosa",
  "genus": "Aristolochia",
  "origin": [
    "Southeastern and south",
    "central United States"
  ],
  "type": "Vine",
  "dimensions": [
    {
      "type": null,
      "min_value": 20,
      "max_value": 30,
      "unit": "feet"
    }
  ],
  "cycle": "Perennial",
  "attracts": [
    "Butterflies"
  ],
  "propagation": [
    "Seed Propagation",
    "Cutting",
    "Layering Propagation",
    "Division"
  ],
  "hardiness": {
    "min": "5",
    "max": "8"
  },
  "hardiness_location": {
    "full_url": "https://perenual.com/api/hardiness-map?species_id=944&size=og&key=sk-kMpx68b02586bb61112084",
    "full_iframe": "<iframe frameborder=0 scrolling=yes seamless=seamless width=1000 height=550 style='margin:auto;' src='https://perenual.com/api/hardiness-map?species_id=944&size=og&key=sk-kMpx68b02586bb61112084'></iframe>"
  },
  "watering": "Average",
  "watering_general_benchmark": {
    "value": "\"3-4\"",
    "unit": "days"
  },
  "plant_anatomy": [
    {
      "part": "leaves",
      "color": [
        "green"
      ]
    },
    {
      "part": "bulb",
      "color": [
        "yellow-green"
      ]
    }
  ],
  "sunlight": [
    "Full sun",
    "part shade"
  ],
  "pruning_month": [
    "February",
    "March",
    "April",
    "June",
    "July",
    "August"
  ],
  "pruning_count": {
    "amount": 1,
    "interval": "yearly"
  },
  "seeds": false,
  "maintenance": "Low",
  "care_guides": "http://perenual.com/api/species-care-guide-list?species_id=944&key=sk-kMpx68b02586bb61112084",
  "soil": [],
  "growth_rate": "Low",
  "drought_tolerant": false,
  "salt_tolerant": false,
  "thorny": false,
  "invasive": true,
  "tropical": false,
  "indoor": false,
  "care_level": "Medium",
  "pest_susceptibility": [],
  "flowers": true,
  "flowering_season": null,
  "cones": false,
  "fruits": false,
  "edible_fruit": false,
  "harvest_season": null,
  "leaf": true,
  "edible_leaf": false,
  "cuisine": false,
  "medicinal": false,
  "poisonous_to_humans": true,
  "poisonous_to_pets": true,
  "description": "The Dutchman's Pipe is truly an amazing plant species. Its exotic floral display can always draw interest and appreciation. Its delicately shaped flowers resemble a meerschaum pipe, hence its name. It is also a hardy plant that is easy to care for. It can thrive in a variety of climates and soils, and can make an attractive addition to any garden. The beautiful blooms of Dutchman's Pipe attract butterflies and hummingbirds with its sweet nectar. The vine can also help create a privacy barrier as it rapidly twines itself up and around a trellis or other structure. These features make the Dutchman's Pipe the perfect choice for any outdoor setting.",
  "default_image": {
    "license": 5,
    "license_name": "Attribution-ShareAlike License",
    "license_url": "https://creativecommons.org/licenses/by-sa/2.0/",
    "original_url": "https://perenual.com/storage/species_image/944_aristolochia_tomentosa/og/46904066822_917f0778b7_b.jpg",
    "regular_url": "https://perenual.com/storage/species_image/944_aristolochia_tomentosa/regular/46904066822_917f0778b7_b.jpg",
    "medium_url": "https://perenual.com/storage/species_image/944_aristolochia_tomentosa/medium/46904066822_917f0778b7_b.jpg",
    "small_url": "https://perenual.com/storage/species_image/944_aristolochia_tomentosa/small/46904066822_917f0778b7_b.jpg",
    "thumbnail": "https://perenual.com/storage/species_image/944_aristolochia_tomentosa/thumbnail/46904066822_917f0778b7_b.jpg"
  },
  "other_images": "Upgrade Plan To Supreme For Access https://perenual.com/subscription-api-pricing. Im sorry",
  "xWateringQuality": "Upgrade Plan To Supreme For Access https://perenual.com/subscription-api-pricing. Im sorry",
  "xWateringPeriod": "Upgrade Plan To Supreme For Access https://perenual.com/subscription-api-pricing. Im sorry",
  "xWateringAvgVolumeRequirement": "Upgrade Plan To Supreme For Access https://perenual.com/subscription-api-pricing. Im sorry",
  "xWateringDepthRequirement": "Upgrade Plan To Supreme For Access https://perenual.com/subscription-api-pricing. Im sorry",
  "xWateringBasedTemperature": "Upgrade Plan To Supreme For Access https://perenual.com/subscription-api-pricing. Im sorry",
  "xWateringPhLevel": "Upgrade Plan To Supreme For Access https://perenual.com/subscription-api-pricing. Im sorry",
  "xSunlightDuration": "Upgrade Plan To Supreme For Access https://perenual.com/subscription-api-pricing. Im sorry",
  "xTemperatureTolence": "Upgrade Plan To Supreme For Access https://perenual.com/subscription-api-pricing. Im sorry",
  "xPlantSpacingRequirement": "Upgrade Plan To Supreme For Access https://perenual.com/subscription-api-pricing. Im sorry"
}