{
  "id": 553,
  "common_name": "California buckeye",
  "scientific_name": [
    "Aesculus californica"
  ],
  "other_name": [],
  "family": "Sapindaceae",
  "hybrid": null,
  "authority": null,
  "subspecies": null,
  "cultivar": null,
  "variety": null,
  "species_epithet": "californica",
  "genus": "Aesculus",
  "origin": [
    "California"
  ],
  "type": "Tree",
  "dimensions": [
    {
      "type": null,
      "min_value": 15,
      "max_value": 30,
      "unit": "feet"
    }
  ],
  "cycle": "Perennial",
  "attracts": [
    "Hummingbirds",
    " Butterflies"
  ],
  "propagation": [
    "Seed Propagation",
    "Cutting",
    "Grafting Propagation",
    "Layering Propagation",
    "Division"
  ],
  "hardiness": {
    "min": "7",
    "max": "8"
  },
  "hardiness_location": {
    "full_url": "https://perenual.com/api/hardiness-map?species_id=553&size=og&key=sk-kMpx68b02586bb61112084",
    "full_iframe": "<iframe frameborder=0 scrolling=yes seamless=seamless width=1000 height=550 style='margin:auto;' src='https://perenual.com/api/hardiness-map?species_id=553&size=og&key=sk-kMpx68b02586bb61112084'></iframe>"
  },
  "watering": "Average",
  "watering_general_benchmark": {
    "value": "\"7-10\"",
    "unit": "days"
  },
  "plant_anatomy": [
    {
      "part": "flowers",
      "color": [
        "pink-white",
        "white-pink",
        "white"
      ]
    },
    {
      "part": "foliage",
      "color": [
        "green"
      ]
    },
    {
      "part": "leaves",
      "color": [
        "green",
        "dark-green"
      ]
    },
    {
      "part": "stems",
      "color": [
        "brown",
        "gray"
      ]
    }
  ],
  "sunlight": [
    "full sun",
    "part shade"
  ],
  "pruning_month": [
    "March",
    "April"
  ],
  "pruning_count": {
    "amount": 1,
    "interval": "yearly"
  },
  "seeds": true,
  "maintenance": "Moderate",
  "care_guides": "http://perenual.com/api/species-care-guide-list?species_id=553&key=sk-kMpx68b02586bb61112084",
  "soil": [],
  "growth_rate": "Low",
  "drought_tolerant": true,
  "salt_tolerant": false,
  "thorny": false,
  "invasive": false,
  "tropical": false,
  "indoor": false,
  "care_level": "Medium",
  "pest_susceptibility": [],
  "flowers": true,
  "flowering_season": null,
  "cones": false,
  "fruits": true,
  "edible_fruit": false,
  "harvest_season": "Fall",
  "leaf": true,
  "edible_leaf": false,
  "cuisine": false,
  "medicinal": true,
  "poisonous_to_humans": true,
  "poisonous_to_pets": true,
  "description": "California buckeye (Aesculus californica) is an amazing ornamental tree with dark brown, coarsely-textured bark complemented by beautiful large, yellow flowers. This tough and long-living species is native to California, where it is highly valued for its ability to tolerate heavy, clay soils and its resilience in wildfires. It is a lovely addition to any outdoor space, providing shade and a colorful seasonal display. In the fall, the green foliage turns to golden yellow, creating a truly stunning landscape. California buckeye is easy to grow and adapts well to most conditions, making it a great option for gardeners of all levels.",
  "default_image": {
    "license": 5,
    "license_name": "Attribution-ShareAlike License",
    "license_url": "https://creativecommons.org/licenses/by-sa/2.0/",
    "original_url": "https://perenual.com/storage/species_image/553_aesculus_californica/og/50050525617_96d27d79d1_b.jpg",
    "regular_url": "https://perenual.com/storage/species_image/553_aesculus_californica/regular/50050525617_96d27d79d1_b.jpg",
    "medium_url": "https://perenual.com/storage/species_image/553_aesculus_californica/medium/50050525617_96d27d79d1_b.jpg",
    "small_url": "https://perenual.com/storage/species_image/553_aesculus_californica/small/50050525617_96d27d79d1_b.jpg",
    "thumbnail": "https://perenual.com/storage/species_image/553_aesculus_californica/thumbnail/50050525617_96d27d79d1_b.jpg"
  },
  "other_images": "Upgrade Plan To Supreme For Access https://perenual.com/subscription-api-pricing. Im sorry",
  "xWateringQuality": "Upgrade Plan To Supreme For Access https://perenual.com/subscription-api-pricing. Im sorry",
  "xWateringPeriod": "Upgrade Plan To Supreme For Access https://perenual.com/subscription-api-pricing. Im sorry",
  "xWateringAvgVolumeRequirement": "Upgrade Plan To Supreme For Access https://perenual.com/subscription-api-pricing. Im sorry",
  "xWateringDepthRequirement": "Upgrade Plan To Supreme For Access https://perenual.com/subscription-api-pricing. Im sorry",
  "xWateringBasedTemperature": "Upgrade Plan To Supreme For Access https://perenual.com/subscription-api-pricing. Im sorry",
  "xWateringPhLevel": "Upgrade Plan To Supreme For Access https://perenual.com/subscription-api-pricing. Im sorry",
  "xSunlightDuration": "Upgrade Plan To Supreme For Access https://perenual.com/subscription-api-pricing. Im sorry",
  "xTemperatureTolence": "Upgrade Plan To Supreme For Access https://perenual.com/subscription-api-pricing. Im sorry",
  "xPlantSpacingRequirement": "Upgrade Plan To Supreme For Access https://perenual.com/subscription-api-pricing. Im sorry"
}